{
  "userID": "61e0ea26b6513705b63998cc",
  "ids": [
    {
      "id": "61e02ce42a2017050fd3da47",
      "time": "2"
    },
    {
      "id": "61e02d422a2017050fd3da48",
      "time": "0"
    },
    {
      "id": "61e02d472a2017050fd3da49",
      "time": "1"
    },
    {
      "id": "61e02d4c2a2017050fd3da4a",
      "time": "2"
    },
    {
      "id": "61e02d592a2017050fd3da4b",
      "time": "2"
    },
    {
      "id": "61e02d672a2017050fd3da4c",
      "time": "0"
    },
    {
      "id": "61e02d802a2017050fd3da4d",
      "time": "2"
    },
    {
      "id": "61e02db62a2017050fd3da4e",
      "time": "0"
    },
    {
      "id": "61e02de22a2017050fd3da4f",
      "time": "0"
    },
    {
      "id": "61e02dec2a2017050fd3da50",
      "time": "2"
    }
  ]
}
